design.sv
module voter_if (I, O);
 input [3:0] I; // I 4 men
 output [3:1] O; // O Result
 reg [3:1] O;

always@ (I)
 begin
    //反對的情況
    case (I) 
        4'b0000: O[3] = 1;
        4'b0001: O[3] = 1;
        4'b0010: O[3] = 1;
        4'b0100: O[3] = 1;
        4'b1000: O[3] = 1;
        default: O[3] = 0; //其餘都為0
    endcase
    //平手的情況
    case (I)
        4'b0011: O[2] = 1;
        4'b0101: O[2] = 1;
        4'b0110: O[2] = 1;
        4'b1001: O[2] = 1;
        4'b1010: O[2] = 1;
        4'b1100: O[2] = 1;
        default: O[2] = 0;  //其餘都為0
    endcase
    //贊成的情況
    case (I)
        4'b1110: O[1] = 1;
        4'b1101: O[1] = 1;
        4'b1011: O[1] = 1;
        4'b0111: O[1] = 1;
        4'b1111: O[1] = 1;
        default: O[1] = 0; //其餘都為0
    endcase
 end
 endmodule

testbench.sv
module vote_tb;
	reg   [3:0] I; //input
	wire  [3:1] O; //output

initial
	begin
	$dumpfile("vote.vcd"); //打開一個vcd數據庫用於紀錄
	$dumpvars(0, s); //要記錄的訊號

	$monitor("I = %b, O = %b ",I,O); //追蹤變數的變化情況
	//將所有input都列在底下
	#10 I = 4'b0000;
	#10 I = 4'b0001;
    #10 I = 4'b0010;
    #10 I = 4'b0011;
    #10 I = 4'b0100;
    #10 I = 4'b0101;
    #10 I = 4'b0110;
    #10 I = 4'b0111;
    #10 I = 4'b1000;
    #10 I = 4'b1001;
    #10 I = 4'b1010;
    #10 I = 4'b1011;
    #10 I = 4'b1100;
    #10 I = 4'b1101;
    #10 I = 4'b1110;
    #10 I = 4'b1111;
	#10 $finish;
	end

	voter_if s(I, O);  //呼叫voter_if
endmodule

vote.vcd
$date
	Mon Apr 25 03:41:20 2022
$end
$version
	Icarus Verilog
$end
$timescale
	1s
$end
$scope module vote_tb $end
$scope module s $end
$var wire 4 ! I [3:0] $end
$var reg 3 " O [3:1] $end
$upscope $end
$upscope $end
$enddefinitions $end
#0
$dumpvars
bx "
bx !
$end
#10
b100 "
b0 !
#20
b1 !
#30
b10 !
#40
b10 "
b11 !
#50
b100 "
b100 !
#60
b10 "
b101 !
#70
b110 !
#80
b1 "
b111 !
#90
b100 "
b1000 !
#100
b10 "
b1001 !
#110
b1010 !
#120
b1 "
b1011 !
#130
b10 "
b1100 !
#140
b1 "
b1101 !
#150
b1110 !
#160
b1111 !
